instanton/__init__.py
instanton/cli.py
instanton/sdk.py
instanton/auth/__init__.py
instanton/auth/middleware.py
instanton/auth/permissions.py
instanton/auth/providers.py
instanton/auth/storage.py
instanton/auth/tokens.py
instanton/client/__init__.py
instanton/client/tcp_tunnel.py
instanton/client/tunnel.py
instanton/client/udp_tunnel.py
instanton/core/__init__.py
instanton/core/config.py
instanton/core/exceptions.py
instanton/core/fast_transport.py
instanton/core/ha.py
instanton/core/loadbalancer.py
instanton/core/performance.py
instanton/core/protocols.py
instanton/core/transport.py
instanton/inspector/__init__.py
instanton/inspector/replay.py
instanton/inspector/server.py
instanton/inspector/storage.py
instanton/observability/__init__.py
instanton/observability/circuit_breaker.py
instanton/observability/health.py
instanton/observability/logging.py
instanton/observability/metrics.py
instanton/observability/tracing.py
instanton/policy/__init__.py
instanton/policy/actions.py
instanton/policy/engine.py
instanton/policy/rules.py
instanton/protocol/__init__.py
instanton/protocol/fast_messages.py
instanton/protocol/messages.py
instanton/security/__init__.py
instanton/security/acme.py
instanton/security/certificates.py
instanton/security/certmanager.py
instanton/security/ddos.py
instanton/security/firewall.py
instanton/security/hardening.py
instanton/security/mtls.py
instanton/security/ratelimit.py
instanton/security/sanitizer.py
instanton/security/tls.py
instanton/security/zerotrust.py
instanton/server/__init__.py
instanton/server/main.py
instanton/server/relay.py
instanton/webhooks/__init__.py
instanton/webhooks/providers.py
instanton/webhooks/verifier.py
instanton-0.8.1.dist-info/METADATA
instanton-0.8.1.dist-info/WHEEL
instanton-0.8.1.dist-info/entry_points.txt
instanton-0.8.1.dist-info/licenses/LICENSE
instanton-0.8.1.dist-info/RECORD
