Metadata-Version: 2.4
Name: instanton
Version: 0.8.1
Summary: Tunnel through barriers, instantly - expose local services to the internet
Project-URL: Homepage, https://github.com/DrRuin/instanton
Project-URL: Documentation, https://github.com/DrRuin/instanton#readme
Project-URL: Repository, https://github.com/DrRuin/instanton
Project-URL: Issues, https://github.com/DrRuin/instanton/issues
Project-URL: Changelog, https://github.com/DrRuin/instanton/releases
Author: Instanton Contributors
License-Expression: MIT
License-File: LICENSE
Keywords: https,localhost,networking,ngrok,proxy,tunnel
Classifier: Development Status :: 3 - Alpha
Classifier: Environment :: Console
Classifier: Intended Audience :: Developers
Classifier: License :: OSI Approved :: MIT License
Classifier: Programming Language :: Python :: 3.11
Classifier: Programming Language :: Python :: 3.12
Classifier: Programming Language :: Python :: 3.13
Classifier: Topic :: Internet :: Proxy Servers
Classifier: Topic :: System :: Networking
Requires-Python: >=3.11
Requires-Dist: aiohttp>=3.13.3
Requires-Dist: aiolimiter>=1.1.0
Requires-Dist: aioquic>=1.3.0
Requires-Dist: anyio>=4.12.1
Requires-Dist: authlib>=1.4.0
Requires-Dist: cachetools>=5.5.0
Requires-Dist: certifi>=2024.12.0
Requires-Dist: click>=8.3.1
Requires-Dist: cryptography>=46.0.3
Requires-Dist: grpcio>=1.76.0
Requires-Dist: h2>=4.3.0
Requires-Dist: httpx>=0.28.1
Requires-Dist: lz4>=4.4.0
Requires-Dist: msgpack>=1.1.0
Requires-Dist: msgspec>=0.20.0
Requires-Dist: opentelemetry-api>=1.30.0
Requires-Dist: opentelemetry-exporter-otlp>=1.30.0
Requires-Dist: opentelemetry-sdk>=1.30.0
Requires-Dist: passlib[argon2]>=1.7.4
Requires-Dist: prometheus-client>=0.23.0
Requires-Dist: psutil>=5.9.0
Requires-Dist: pydantic>=2.12.5
Requires-Dist: python-jose[cryptography]>=3.3.0
Requires-Dist: rich>=14.2.0
Requires-Dist: structlog>=25.5.0
Requires-Dist: uvloop>=0.22.0; sys_platform != 'win32'
Requires-Dist: websockets>=15.0.1
Requires-Dist: zstandard>=0.25.0
Provides-Extra: dev
Requires-Dist: mypy>=1.15.0; extra == 'dev'
Requires-Dist: pre-commit>=4.2.0; extra == 'dev'
Requires-Dist: pytest-asyncio>=1.3.0; extra == 'dev'
Requires-Dist: pytest-benchmark>=5.2.0; extra == 'dev'
Requires-Dist: pytest-cov>=6.0.0; extra == 'dev'
Requires-Dist: pytest>=9.0.2; extra == 'dev'
Requires-Dist: ruff>=0.14.10; extra == 'dev'
Requires-Dist: types-cachetools>=5.5.0; extra == 'dev'
